FATS
