Metadata-Version: 1.1
Name: FATS
Version: 1.3.3
Summary: Library with compilation of features for time series
Home-page:  http://isadoranun.github.io/tsfeat/FeaturesDocumentation.html
Author: Isadora Nun
Author-email: isadoranun@seas.harvard.edu
License: MIT licence
Download-URL: https://github.com/isadoranun/tsfeat
Keywords: times series features,light curves
Platform: UNKNOWN
Classifier: Development Status :: 3 - Alpha
Classifier: Intended Audience :: Science/Research
Classifier: Topic :: Scientific/Engineering :: Astronomy
Classifier: Topic :: Software Development :: Libraries :: Python Modules
Classifier: Programming Language :: Python :: 2
Classifier: Programming Language :: Python :: 2.6
Classifier: Programming Language :: Python :: 2.7
Classifier: Programming Language :: Python :: 3
Classifier: Programming Language :: Python :: 3.2
Classifier: Programming Language :: Python :: 3.3
Classifier: Programming Language :: Python :: 3.4
